pgdsn2env/__init__.py
pgdsn2env/__main__.py
pgdsn2env/_cli.py
pgdsn2env/_const.py
pgdsn2env/_core.py
pgdsn2env/py.typed
pgdsn2env-1.1.0.dist-info/WHEEL
pgdsn2env-1.1.0.dist-info/entry_points.txt
pgdsn2env-1.1.0.dist-info/METADATA
pgdsn2env-1.1.0.dist-info/RECORD
