Metadata-Version: 2.3
Name: pgdsn2env
Version: 1.1.0
Summary: Parse PostgreSQL DSNs into PG* environment variables with export helpers.
Author: Fai
Author-email: Fai <lamkafai1997@gmail.com>
Classifier: Development Status :: 4 - Beta
Classifier: Intended Audience :: Developers
Classifier: Intended Audience :: System Administrators
Classifier: Operating System :: OS Independent
Classifier: Programming Language :: Python :: 3 :: Only
Classifier: Programming Language :: Python :: 3.10
Classifier: Programming Language :: Python :: 3.11
Classifier: Programming Language :: Python :: 3.12
Classifier: Programming Language :: Python :: 3.13
Classifier: Programming Language :: Python :: 3.14
Classifier: Topic :: Database
Classifier: Topic :: Utilities
Requires-Python: >=3.10
Project-URL: Changelog, https://github.com/kafai-lam/pgdsn2env/releases
Project-URL: Documentation, https://github.com/kafai-lam/pgdsn2env/blob/main/README.md
Project-URL: Homepage, https://github.com/kafai-lam/pgdsn2env
Project-URL: Issues, https://github.com/kafai-lam/pgdsn2env/issues
Project-URL: Repository, https://github.com/kafai-lam/pgdsn2env
